Metadata-Version: 1.0
Name: shay-dists
Version: 1.0
Summary: Gaussian and Binomial distribution classes.
Home-page: UNKNOWN
Author: Aian Shay
Author-email: aianshay@gmail.com
License: UNKNOWN
Platform: UNKNOWN
